sasapay_payments/__init_.py
sasapay_payments/auth.py
sasapay_payments/payments.py
sasapay_payments/services.py
sasapay_payments-1.0.1.dist-info/LICENSE.txt
sasapay_payments-1.0.1.dist-info/METADATA
sasapay_payments-1.0.1.dist-info/WHEEL
sasapay_payments-1.0.1.dist-info/top_level.txt
sasapay_payments-1.0.1.dist-info/RECORD
